livestreamer_curses
