Metadata-Version: 1.1
Name: livestreamer-curses
Version: 1.5.2
Summary: Livestreamer-curses is a curses frontend to livestreamer
Home-page: http://github.com/gapato/livestreamer-curses
Author: Gapato
Author-email: g@oknaj.eu
License: MIT
Platform: UNKNOWN
Classifier: Operating System :: POSIX
Classifier: Programming Language :: Python :: 2
Classifier: Programming Language :: Python :: 3
Classifier: Environment :: Console :: Curses
Classifier: Development Status :: 4 - Beta
Classifier: License :: OSI Approved :: MIT License
Classifier: Topic :: Utilities
